gb2260_v2/__init__.py
gb2260_v2/_compat.py
gb2260_v2/code.py
gb2260_v2/division.py
gb2260_v2/exceptions.py
gb2260_v2/gb2260.py
gb2260_v2/revision.py
gb2260_v2/data/__init__.py
gb2260_v2/data/curated/__init__.py
gb2260_v2/data/curated/revision_198012.py
gb2260_v2/data/curated/revision_198112.py
gb2260_v2/data/curated/revision_198212.py
gb2260_v2/data/curated/revision_198312.py
gb2260_v2/data/curated/revision_198412.py
gb2260_v2/data/curated/revision_198512.py
gb2260_v2/data/curated/revision_198612.py
gb2260_v2/data/curated/revision_198712.py
gb2260_v2/data/curated/revision_198812.py
gb2260_v2/data/curated/revision_198912.py
gb2260_v2/data/curated/revision_199012.py
gb2260_v2/data/curated/revision_199112.py
gb2260_v2/data/curated/revision_199212.py
gb2260_v2/data/curated/revision_199312.py
gb2260_v2/data/curated/revision_199412.py
gb2260_v2/data/curated/revision_199512.py
gb2260_v2/data/curated/revision_199612.py
gb2260_v2/data/curated/revision_199712.py
gb2260_v2/data/curated/revision_199812.py
gb2260_v2/data/curated/revision_199912.py
gb2260_v2/data/curated/revision_200012.py
gb2260_v2/data/curated/revision_200112.py
gb2260_v2/data/curated/revision_200212.py
gb2260_v2/data/curated/revision_200306.py
gb2260_v2/data/curated/revision_200312.py
gb2260_v2/data/curated/revision_200403.py
gb2260_v2/data/curated/revision_200409.py
gb2260_v2/data/curated/revision_200412.py
gb2260_v2/data/curated/revision_200506.py
gb2260_v2/data/curated/revision_200512.py
gb2260_v2/data/curated/revision_200612.py
gb2260_v2/data/curated/revision_200712.py
gb2260_v2/data/curated/revision_200812.py
gb2260_v2/data/curated/revision_200912.py
gb2260_v2/data/curated/revision_201010.py
gb2260_v2/data/curated/revision_201012.py
gb2260_v2/data/curated/revision_201110.py
gb2260_v2/data/curated/revision_201112.py
gb2260_v2/data/curated/revision_201210.py
gb2260_v2/data/curated/revision_201308.py
gb2260_v2/data/curated/revision_201312.py
gb2260_v2/data/curated/revision_201410.py
GB2260_v2-0.2.1.dist-info/LICENSE
GB2260_v2-0.2.1.dist-info/METADATA
GB2260_v2-0.2.1.dist-info/WHEEL
GB2260_v2-0.2.1.dist-info/top_level.txt
GB2260_v2-0.2.1.dist-info/RECORD
